shrinkit/__init__.py
shrinkit/__version__.py
shrinkit/encoding.py
shrinkit/evaluation.py
shrinkit/filtration.py
shrinkit/imputation.py
shrinkit/machine_learning.py
shrinkit/main.py
shrinkit/normalization.py
shrinkit/runner.py
shrinkit/ml/__init__.py
shrinkit/ml/encoding.py
shrinkit/ml/evaluation.py
shrinkit/ml/filtration.py
shrinkit/ml/imputation.py
shrinkit/ml/machine_learning.py
shrinkit/ml/normalization.py
shrinkit/ml/runner.py
shrinkit-0.1.11.dist-info/LICENSE
shrinkit-0.1.11.dist-info/METADATA
shrinkit-0.1.11.dist-info/WHEEL
shrinkit-0.1.11.dist-info/top_level.txt
shrinkit-0.1.11.dist-info/RECORD
