Metadata-Version: 2.1
Name: shrinkit
Version: 0.1.11
Summary: The package that helps to compress everything for ML/AI projects.
Home-page: https://github.com/blurred-machine/shrinkit
Author: Paras Varshney
Author-email: paras.varshney97@gmail.com
License: MIT
Platform: UNKNOWN
Classifier: License :: OSI Approved :: MIT License
Classifier: Programming Language :: Python
Classifier: Programming Language :: Python :: 3
Classifier: Programming Language :: Python :: 3.11
Classifier: Programming Language :: Python :: Implementation :: CPython
Classifier: Programming Language :: Python :: Implementation :: PyPy
Requires-Python: >=3.10.0
License-File: LICENSE
Requires-Dist: numpy
Requires-Dist: pandas
Requires-Dist: scikit-learn
Requires-Dist: scipy
Requires-Dist: streamlit
Requires-Dist: streamlit-ydata-profiling
Requires-Dist: ydata-profiling
